Metadata-Version: 2.1
Name: aviasales
Version: 0.0.1
Summary: Pirate API for aviasales.ru
Home-page: https://github.com/masterbpro/aviasales_api
Author: akbarov
Author-email: iserver12345@gmail.com
License: MIT
